fastpurge/__init__.py
fastpurge/_client.py
fastpurge-1.0.6.dist-info/LICENSE
fastpurge-1.0.6.dist-info/METADATA
fastpurge-1.0.6.dist-info/WHEEL
fastpurge-1.0.6.dist-info/top_level.txt
fastpurge-1.0.6.dist-info/RECORD
