Metadata-Version: 2.1
Name: fastpurge
Version: 1.0.6
Summary: A client for the Akamai Fast Purge API
Home-page: https://github.com/release-engineering/python-fastpurge
License: GNU General Public License
Project-URL: Documentation, https://release-engineering.github.io/python-fastpurge/
Project-URL: Changelog, https://github.com/release-engineering/python-fastpurge/blob/master/CHANGELOG.md
Classifier: Development Status :: 5 - Production/Stable
Classifier: Intended Audience :: Developers
Classifier: License :: OSI Approved :: GNU General Public License v3 or later (GPLv3+)
Classifier: Programming Language :: Python :: 3
Classifier: Topic :: Software Development :: Libraries :: Python Modules
Requires-Python: >=3.6
License-File: LICENSE
Requires-Dist: requests
Requires-Dist: more-executors>=2.7.0
Requires-Dist: six
Requires-Dist: edgegrid-python
Requires-Dist: monotonic; python_version < "3.3"
